omnivore_api/__init__.py
omnivore_api/api.py
omnivore_api/models.py
omnivore_api/queries/ApplyLabels.graphql
omnivore_api/queries/ArchiveSavedItem.graphql
omnivore_api/queries/ArticleContent.graphql
omnivore_api/queries/CreateHighlight.graphql
omnivore_api/queries/CreateLabel.graphql
omnivore_api/queries/DeleteHighlight.graphql
omnivore_api/queries/DeleteLabel.graphql
omnivore_api/queries/DeleteSavedItem.graphql
omnivore_api/queries/GetSubscriptions.graphql
omnivore_api/queries/Labels.graphql
omnivore_api/queries/MergeHighlight.graphql
omnivore_api/queries/ReadingProgressMutation.graphql
omnivore_api/queries/SavePage.graphql
omnivore_api/queries/SaveUrl.graphql
omnivore_api/queries/Search.graphql
omnivore_api/queries/TypeAheadSearch.graphql
omnivore_api/queries/UpdateHighlight.graphql
omnivore_api/queries/UpdateLabel.graphql
omnivore_api/queries/UpdatePage.graphql
omnivore_api/queries/UpdatesSince.graphql
omnivore_api/queries/ValidateUsername.graphql
omnivore_api/queries/Viewer.graphql
omnivore_api/queries/schema.graphqls
omnivore_api-0.4.0.dist-info/licenses/LICENSE
omnivore_api-0.4.0.dist-info/METADATA
omnivore_api-0.4.0.dist-info/WHEEL
omnivore_api-0.4.0.dist-info/top_level.txt
omnivore_api-0.4.0.dist-info/RECORD
