Metadata-Version: 2.4
Name: omnivore_api
Version: 0.4.0
Summary: Omnivore API Client for Python
Home-page: https://github.com/Benature/OmnivoreAPI
Author: Benature
Author-email: 
License: MIT
Project-URL: Bug Tracker, https://github.com/Benature/OmnivoreAPI/issues
Project-URL: Source Code, https://github.com/Benature/OmnivoreAPI
Keywords: omnivore api readlater graphql gql client
Platform: any
Classifier: Intended Audience :: Developers
Classifier: Topic :: Software Development :: Libraries
Classifier: Programming Language :: Python :: 3
Classifier: License :: OSI Approved :: MIT License
Requires-Python: >=3
License-File: LICENSE
Requires-Dist: python-dotenv
Requires-Dist: gql>=3.5.0
Requires-Dist: requests-toolbelt>=1.0.0
Dynamic: author
Dynamic: classifier
Dynamic: description
Dynamic: description-content-type
Dynamic: home-page
Dynamic: keywords
Dynamic: license
Dynamic: license-file
Dynamic: platform
Dynamic: project-url
Dynamic: requires-dist
Dynamic: requires-python
Dynamic: summary
